recurrent_memory_transformer_pytorch/__init__.py
recurrent_memory_transformer_pytorch/attend.py
recurrent_memory_transformer_pytorch/recurrent_memory_transformer.py
recurrent_memory_transformer_pytorch-0.7.0.dist-info/LICENSE
recurrent_memory_transformer_pytorch-0.7.0.dist-info/METADATA
recurrent_memory_transformer_pytorch-0.7.0.dist-info/WHEEL
recurrent_memory_transformer_pytorch-0.7.0.dist-info/top_level.txt
recurrent_memory_transformer_pytorch-0.7.0.dist-info/RECORD
