Metadata-Version: 2.1
Name: recurrent-memory-transformer-pytorch
Version: 0.7.0
Summary: Recurrent Memory Transformer - Pytorch
Home-page: https://github.com/lucidrains/recurrent-memory-transformer-pytorch
Author: Phil Wang
Author-email: lucidrains@gmail.com
License: MIT
Keywords: artificial intelligence,deep learning,transformers,attention mechanism,recurrence,memory,long-context
Classifier: Development Status :: 4 - Beta
Classifier: Intended Audience :: Developers
Classifier: Topic :: Scientific/Engineering :: Artificial Intelligence
Classifier: License :: OSI Approved :: MIT License
Classifier: Programming Language :: Python :: 3.6
License-File: LICENSE
Requires-Dist: einops>=0.8.0
Requires-Dist: hyper-connections>=0.1.7
Requires-Dist: torch>=2.3
